<?xml version="1.0" encoding="utf-8"?>
<text type="diary"><group><text n="41000000000" xml:id="DKB10011m"><body><div type="diary-entry" xml:id="DKB10011m-0313"><p><persName corresp="#pers_堀越角次郎"><forename>
         次郎
        </forename>
</persName>
       氏姉弟二人来ル、家事ニ関シテ余ノ添心ヲ依頼スルタメナリ、姉ニ配スル婿ノ人撰ノ事ニ付談話アリ、午飧ヲ共ニシテ帰リ去ル、午後書類ヲ整理ス
      </p>
</div>
<div type="diary-entry" xml:id="DKB10011m-0314">
<head>
<date when="1903-06-29">
        六月廿九日
       </date>
</head>
<p>
       晴、
       <time when="08:00:00">
        午前八時
       </time>
       朝飧ヲ畢リ書状数通ヲ裁シ且書類ヲ整理ス、
       <time when="13:00:00">
        午後一時
       </time>
       日本鉄道会社ニ抵リ去ル金曜日ノ重役会ニ欠席セシニ付テ当日ノ議案ヲ一覧ス、
       <time when="14:00:00">
        午後二時
       </time>
<placeName corresp="#place_日本橋兜町">
        兜町
       </placeName>
       事務所ニ抵リ数多ノ来人ニ接ス、新聞記者多ク来リテ時事ヲ問ハル、
       <time when="15:00:00">
        三時
       </time>
<persName corresp="#pers_千家尊福">
<surname>
         千家
        </surname>
</persName>
       府知事ト共ニ東京電車鉄道ト市街鉄道トノ合併ニ関シ覚書ヲ両会社重役ニ交付ス、電車ヨリ
       <persName corresp="#pers_牟田口">
<surname>
         牟田口
        </surname>
</persName>
       、
       <persName corresp="#pers_中野">
<surname>
         中野
        </surname>
</persName>
       、市街ヨリハ
       <persName corresp="#pers_藤山">
<surname>
         藤山
        </surname>
</persName>
       、
       <persName corresp="#pers_野中">
<surname>
         野中
        </surname>
</persName>
       、
       <persName corresp="#pers_吉田">
<surname>
         吉田
        </surname>
</persName>
       三氏来会ス、畢テ
       <time when="16:00:00">
        午後四時
       </time>
       深川区役所ニ抵リ区会ヲ開ク、
       <time when="19:00:00">
        午後七時
       </time>
       閉会、
       <placeName corresp="#place_清澄_(江東区)">
        清澄町
       </placeName>
<persName corresp="#pers_臼井">
<surname>
         臼井
        </surname>
</persName>
       氏宅ニ抵リ浦賀船渠会社重役会ニ参列ス、
       <time when="21:00:00">
        九時
       </time>
<placeName corresp="#place_日本橋兜町">
        兜町
       </placeName>
       事務所ニ抵リ
       <persName corresp="#pers_渋沢作太郎">
<surname>
         渋沢
        </surname>
<forename>
         作太郎
        </forename>
</persName>
       、
       <persName corresp="#pers_書上">
<surname>
         書上
        </surname>
</persName>
       、
       <persName corresp="#pers_桃井">
<surname>
         桃井
        </surname>
</persName>
       二氏《（三）》ニ会話シテ
       <placeName corresp="#place_白金">
        白金
       </placeName>
       ノ不都合行為ニ付処分方法ヲ協議ス、
       <persName corresp="#pers_和田格太郎">
<surname>
         和田
        </surname>
<forename>
         格太郎
        </forename>
</persName>
       来リ同シク
       <placeName corresp="#place_白金">
        白金
       </placeName>
       身上ノ事ヲ談ス、
       <time when="12:00:00">
        十二時
       </time>
       ヨリ同族会ヲ開キ
       <time when="14:00:00">
        二時
       </time>
       散会、夜
       <time when="15:00:00">
        三時
       </time>
<placeName corresp="#place_飛鳥山邸">
        王子別荘
       </placeName>
       ニ帰宿ス
      </p>
</div>
<div type="diary-entry" xml:id="DKB10011m-0315">
<head>
<date when="1903-06-30">
        六月三十日
       </date>
</head>
<p>
       晴、
       <time when="08:00:00">
        午前八時
       </time>
       朝飧ヲ畢リ、
       <time when="10:00:00">
        十時
       </time>
       宮内省ニ抵ル、大臣、次官トモニ出省ナキヲ以テ名刺ヲ留メテ去ル、
       <time when="11:00:00">
        十一時
       </time>
       磐城炭坑会社ニ抵リ重役会ニ列ス、畢テ
       <orgName>
        第一銀行
       </orgName>
       ニ抵リテ午飧ス、
       <persName corresp="#pers_宇野保太郎">
<surname>
         宇野
        </surname>
<forename>
         保太郎
        </forename>
</persName>
       氏来リ製麻会社善後処分ノ事ヲ談ス、
       <persName corresp="#pers_日下義雄">
<surname>
         日下
        </surname>
<forename>
         義雄
        </forename>
</persName>
       氏来リテ
       <orgName>
        七十七銀行
       </orgName>
       業務改良方針ニ関シ、其調査書類ヲ以テ得失ヲ討議ス、
       <time when="14:00:00">
        午後二時
       </time>
<persName corresp="#pers_前島">
<surname>
         前島
        </surname>
</persName>
       、
       <persName corresp="#pers_塚原">
<surname>
         塚原
        </surname>
</persName>
       、
       <persName corresp="#pers_富岡">
<surname>
         富岡
        </surname>
</persName>
       ノ三氏来リテ、浦賀船渠会社ニテ製造シタルヒリツピン政府ヨリ注文ノ船舶ニ関シテ将来ノ処分方法ヲ協議ス、
       <time when="16:00:00">
        午後四時
       </time>
<orgName>
        日本煉瓦会社
       </orgName>
       事務所ニ抵リ埼玉誘掖会評議員会ヲ開ク、
       <time when="17:00:00">
        五時
       </time>
       再ヒ
       <orgName>
        第一銀行
       </orgName>
       ニ抵リ、
       <placeName corresp="#place_仙台">
        仙台
       </placeName>
<orgName>
        七十七銀行
       </orgName>
       整理ニ関シ、
       <persName corresp="#pers_平岡">
<surname>
         平岡
        </surname>
</persName>
       書記官、
       <persName corresp="#pers_早川">
<surname>
         早川
        </surname>
</persName>
       市長、
       <persName corresp="#pers_遠藤頭取">
<surname>
         遠藤
        </surname>
        頭取
       </persName>
       、
       <persName corresp="#pers_大森">
<surname>
         大森
        </surname>
</persName>
       監査役等ニ会話ス、
       <persName corresp="#pers_佐々木">
<surname>
         佐々木
        </surname>
</persName>
       支配人同席ス、
       <time when="18:00:00">
        午後六時
       </time>
       過談畢テ、
       <persName corresp="#pers_堀越">
<surname>
         堀越
        </surname>
</persName>
       、
       <persName corresp="#pers_赤羽">
<surname>
         赤羽
        </surname>
</persName>
       二氏ノ来訪ニ接シ、
       <time when="19:30:00">
        七時半
       </time>
<placeName corresp="#place_浜町">
        浜町
       </placeName>
       宅ニ帰宿ス
      </p>
</div>
<div type="diary-entry" xml:id="DKB10011m-0316">
<head>
<date when="1903-07-01">
        七月一日
       </date>
</head>
<p>
       雨、
       <time when="08:00:00">
        午前八時
       </time>
       朝飧ヲ畢リ、大蔵大臣ヲ官舎ニ訪ヒ、更ニ大蔵省ニ抵リ
       <persName corresp="#pers_阪谷">
<surname>
         阪谷
        </surname>
</persName>
       、
       <persName corresp="#pers_松尾">
<surname>
         松尾
        </surname>
</persName>
       二氏ニ面会ス、
       <time when="10:00:00">
        十時
       </time>
<placeName corresp="#place_日本橋兜町">
        兜町
       </placeName>
       事務所ニ抵ル、種々ノ来人ニ接シ書類ヲ整理ス、
       <time when="14:00:00">
        午後二時
       </time>
<orgName>
        日本郵船会社
       </orgName>
       重役会ニ出席ス、畢テ
       <placeName corresp="#place_日本橋兜町">
        兜町
       </placeName>
       ニ抵リ夜
       <placeName corresp="#place_飛鳥山邸">
        王子別荘
       </placeName>
       ニ帰宿ス
      </p>
</div>
<div type="diary-entry" xml:id="DKB10011m-0317">
<head>
<date when="1903-07-02">
        七月二日
       </date>
</head>
<p>
       曇、
       <time when="08:00:00">
        午前八時
       </time>
       朝飧ヲ畢リ、
       <persName corresp="#pers_山本">
<surname>
         山本
        </surname>
</persName>
       総裁ヲ其宅ニ訪ヒ京釜鉄道会社社債ノ事ヲ談ス、
       <time when="10:00:00">
        十時
       </time>
<placeName corresp="#place_日本橋兜町">
        兜町
       </placeName>
       事務所ニ抵リテ来客ニ面会ス、
       <time when="14:00:00">
        午後二時
       </time>
<orgName>
        第一銀行
       </orgName>
       重役会ニ出席ス、畢テ
       <placeName corresp="#place_日本橋兜町">
        兜町
       </placeName>
       ニ於テ書類ヲ一覧シ、夜
       <placeName corresp="#place_飛鳥山邸">
        王子別荘
       </placeName>
       ニ帰宿ス
      </p>
</div>
<div type="diary-entry" xml:id="DKB10011m-0318">
<head>
<date when="1903-07-03">
        七月三日
       </date>
</head>
<p>
       晴、
       <time when="08:00:00">
        午前八時
       </time>
       朝飧ヲ畢リ、
       <time when="10:00:00">
        十時
       </time>
<placeName corresp="#place_日本橋兜町">
        兜町
       </placeName>
       事務所ニ抵リ来人ニ接ス、午後日本鉄道会社重役会ニ出席ス、夜
       <placeName corresp="#place_浜町">
        浜町
       </placeName>
       宅ニ帰宿ス
      </p>
</div>
<div type="diary-entry" xml:id="DKB10011m-0319">
<head>
<date when="1903-07-04">
        七月四日
       </date>
</head>
<p>
       晴、
       <time when="08:00:00">
        午前八時
       </time>
       朝飧ヲ畢リ、
       <time when="09:00:00">
        九時
       </time>
<placeName corresp="#place_日本橋兜町">
        兜町
       </placeName>
       事務所ニ抵リ浦賀船渠会社重役会ニ出席ス、午後京釜鉄道会社常務取締役来会シ社債ニ関スル事ヲ談ス夕方
       <placeName corresp="#place_飛鳥山邸">
        王子別荘
       </placeName>
       ニ帰宿ス
      </p>
</div>
<div type="diary-entry" xml:id="DKB10011m-0320">
<head>
<date when="1903-07-05">
        七月五日
       </date>
</head>
<p>
<pb corresp="#pageB1317" facs="https://eiichi.shibusawa.or.jp/denkishiryo-bekkan/api/images/iiif/343/full/max/0/default.jpg" n="B1317" source="#pageB1317"></pb>
</p>
</div>
</body>
</text>
</group>
</text>