<?xml version="1.0" encoding="utf-8"?>
<text type="diary"><group><text n="41000000000" xml:id="DKB10009m"><body><div type="diary-entry" xml:id="DKB10009m-0433"><p>
       午餐ス、
       <time when="15:00:00">
        午後三時
       </time>
<persName corresp="#pers_大倉">
<surname>
         大倉
        </surname>
</persName>
       氏ト共ニ大倉商業学校ニ抵リ生徒ニ対シテ一場ノ演説ヲ為ス、
       <time when="15:00:00">
        三時
       </time>
<placeName corresp="#place_日本橋兜町">
        兜町
       </placeName>
       ニ帰ル、仏国人
       <persName corresp="#pers_ブヱリツピ">
<surname>
         ブヱリツピ
        </surname>
</persName>
       氏来ル、同氏ハ
       <placeName corresp="#place_横浜">
        横浜
       </placeName>
<placeName corresp="#place_神戸">
        神戸
       </placeName>
       ニ商店ヲ有スル輸出入貿易ヲ営ムモノニシテ、
       <persName corresp="#pers_アルベルト_カン">
<forename>
         アルベルト
        </forename>
        ・
        <surname>
         カン
        </surname>
</persName>
       氏ノ紹介ヲ以テ来レルナリ、款談数時
       <time when="18:00:00">
        六時
       </time>
       頃分袂ス、夜餐後銀行集会所ニ抵リ
       <orgName>
        竜門社
       </orgName>
       月次会ニ列ス、夜
       <time when="22:00:00">
        十時
       </time>
       帰宅ス
      </p>
</div>
<div type="diary-entry" xml:id="DKB10009m-0434">
<head>
<date when="1901-03-10">
        三月十日
       </date>
</head>
<p>
       晴、午前、
       <persName corresp="#pers_長谷川">
<surname>
         長谷川
        </surname>
</persName>
       某来ル、
       <persName corresp="#pers_高野積成">
<surname>
         高野
        </surname>
<forename>
         積成
        </forename>
</persName>
       来ル、葡萄酒ノ事ヲ談ス、
       <persName corresp="#pers_木内善兵衛">
<surname>
         木内
        </surname>
<forename>
         善兵衛
        </forename>
</persName>
       来ル、野沢倉庫会社ヘ金融ノ事ヲ依頼セラル、
       <persName corresp="#pers_岩出惣兵衛">
<surname>
         岩出
        </surname>
<forename>
         惣兵衛
        </forename>
</persName>
       、
       <persName corresp="#pers_竹沢太一">
<surname>
         竹沢
        </surname>
<forename>
         太一
        </forename>
</persName>
       諸氏来話ス、
       <time when="12:00:00">
        十二時
       </time>
<persName corresp="#pers_浅田正文">
<surname>
         浅田
        </surname>
<forename>
         正文
        </forename>
</persName>
       氏ト谷ノ宅ヲ訪ヒ其催ス処ノ茶事ニ会ス、
       <persName corresp="#pers_朝吹英二">
<surname>
         朝吹
        </surname>
<forename>
         英二
        </forename>
</persName>
       、
       <persName corresp="#pers_平岡浩太郎">
<surname>
         平岡
        </surname>
<forename>
         浩太郎
        </forename>
</persName>
       、
       <persName corresp="#pers_高橋義雄_(茶人)">
<surname>
         高橋
        </surname>
<forename>
         義雄
        </forename>
</persName>
       諸氏来会ス、
       <time when="17:00:00">
        午後五時
       </time>
       散会、
       <time when="18:00:00">
        六時
       </time>
<placeName corresp="#place_浜町">
        浜町
       </placeName>
       常盤屋ニ抵ル、十日会ニ列スルナリ、
       <persName corresp="#pers_菊地">
<surname>
         菊地
        </surname>
</persName>
       、
       <persName corresp="#pers_馬越">
<surname>
         馬越
        </surname>
</persName>
       、
       <persName corresp="#pers_岩出">
<surname>
         岩出
        </surname>
</persName>
       ノ諸氏来会ス、夜
       <time when="22:00:00">
        十時
       </time>
<placeName corresp="#place_浜町">
        浜町
       </placeName>
       ニ帰宿ス
      </p>
</div>
<div type="diary-entry" xml:id="DKB10009m-0435">
<head>
<date when="1901-03-11">
        三月十一日
       </date>
</head>
<p>
       曇、
       <time when="09:00:00">
        午前九時
       </time>
       商業会議所役員会ニ出席シ仲裁判断ノ事ヲ談ス、
       <time when="11:00:00">
        十一時
       </time>
       海上保険会社ニ抵リ重役会ニ列ス、
       <time when="14:00:00">
        午後二時
       </time>
       外務省ニ抵リ大臣ニ面会シ京釜鉄道ノ事ヲ談話ス、
       <time when="16:00:00">
        四時
       </time>
<orgName>
        第一銀行
       </orgName>
       ニ出勤ス、
       <persName corresp="#pers_今村">
<surname>
         今村
        </surname>
</persName>
       氏来ル、
       <persName corresp="#pers_平岡熙">
<surname>
         平岡
        </surname>
<forename>
         熙
        </forename>
</persName>
       ニ書状ヲ発ス、夜
       <placeName corresp="#place_日本橋兜町">
        兜町
       </placeName>
       ニ帰ル、
       <placeName corresp="#place_新潟">
        新潟
       </placeName>
<persName corresp="#pers_松井吉太郎">
<surname>
         松井
        </surname>
<forename>
         吉太郎
        </forename>
</persName>
       、大坂
       <persName corresp="#pers_長谷川一彦">
<surname>
         長谷川
        </surname>
<forename>
         一彦
        </forename>
</persName>
       、
       <placeName corresp="#place_神戸">
        神戸
       </placeName>
<persName corresp="#pers_熊谷辰太郎">
<surname>
         熊谷
        </surname>
<forename>
         辰太郎
        </forename>
</persName>
       二氏《（三）》ヘ書状ヲ発ス
      </p>
</div>
<div type="diary-entry" xml:id="DKB10009m-0436">
<head>
<date when="1901-03-12">
        三月十二日
       </date>
</head>
<p>
       晴、午前数多ノ来人ニ接ス、
       <persName corresp="#pers_村山藤太">
<surname>
         村山
        </surname>
<forename>
         藤太
        </forename>
</persName>
       （
       <placeName corresp="#place_釜山広域市">
        釜山
       </placeName>
       京坂亭主人）、
       <persName corresp="#pers_村上彰一">
<surname>
         村上
        </surname>
<forename>
         彰一
        </forename>
</persName>
       、
       <persName corresp="#pers_山田昌邦">
<surname>
         山田
        </surname>
<forename>
         昌邦
        </forename>
</persName>
       、
       <persName corresp="#pers_大原春次郎">
<surname>
         大原
        </surname>
<forename>
         春次郎
        </forename>
</persName>
       諸氏来ル、午後
       <orgName>
        帝国大学
       </orgName>
       ニ抵リ
       <persName corresp="#pers_菊池">
<surname>
         菊池
        </surname>
</persName>
       総長ニ面会シテ養育院医員ノ事、
       <persName corresp="#pers_渡辺">
<surname>
         渡辺
        </surname>
</persName>
       博士ノ事、及
       <orgName>
        商業大学
       </orgName>
       ノ事等ヲ談話ス、後文部省ニ抵リ梅次官ニ面会シテ
       <orgName>
        商業大学
       </orgName>
       ノ事ヲ談ス、
       <time when="15:00:00">
        午後三時
       </time>
       過瓦斯会社重役会ニ列ス、畢テ
       <orgName>
        日本銀行
       </orgName>
       ニ抵リ
       <persName corresp="#pers_山本">
<surname>
         山本
        </surname>
</persName>
       総裁ニ面会シテ経済上ノ事、及興信所ノ事ヲ談ス、
       <time when="16:00:00">
        午後四時
       </time>
       銀行集会所ニ抵リ銀行条例改正委員会ニ列ス、畢テ夜
       <placeName corresp="#place_深川">
        深川
       </placeName>
       宅ニ帰宿ス
      </p>
</div>
<div type="diary-entry" xml:id="DKB10009m-0437">
<head>
<date when="1901-03-13">
        三月十三日
       </date>
</head>
<p>
       晴、午前、
       <persName corresp="#pers_井上">
<surname>
         井上
        </surname>
</persName>
       伯ヲ
       <placeName corresp="#place_麻布">
        麻布
       </placeName>
       ノ邸ニ訪ヒ、
       <time when="11:00:00">
        十一時
       </time>
<orgName>
        銀行倶楽部
       </orgName>
       ニ抵リ興信所評議員会ニ列ス、畢テ
       <orgName>
        日本郵船会社
       </orgName>
       重役会ニ列ス、又商業会議所ニ抵リ仲裁判断ノ事其他ノ事ヲ協議ス、夜
       <orgName>
        銀行倶楽部
       </orgName>
       ニ抵リ商業学校出身ノ諸氏ト
       <orgName>
        商業大学
       </orgName>
       ノ事ヲ談ス、夜
       <time when="22:00:00">
        十時
       </time>
<placeName corresp="#place_日本橋兜町">
        兜町
       </placeName>
       ニ帰宅ス
      </p>
</div>
<div type="diary-entry" xml:id="DKB10009m-0438">
<head>
<date when="1901-03-14">
        三月十四日
       </date>
</head>
<p>
       晴、午前数多ノ来人ニ接ス、午後
       <persName corresp="#pers_原">
<surname>
         原
        </surname>
</persName>
       逓信大臣ヲ官舎ニ訪ヒ京釜鉄道ノ事ヲ談ス、宮内省ニ抵リ
       <persName corresp="#pers_田中">
<surname>
         田中
        </surname>
</persName>
       大臣ニ面会シテ京釜鉄道株ノ事ヲ談ス、
       <time when="14:00:00">
        午後二時
       </time>
<orgName>
        第一銀行
       </orgName>
       重役会ニ列ス、畢テ
       <placeName corresp="#place_日本橋兜町">
        兜町
       </placeName>
       宅ニ帰ル、此夜、
       <persName corresp="#pers_尾崎">
<surname>
         尾崎
        </surname>
</persName>
       、
       <persName corresp="#pers_竹内">
<surname>
         竹内
        </surname>
</persName>
       、
       <persName corresp="#pers_日下">
<surname>
         日下
        </surname>
</persName>
       、
       <persName corresp="#pers_井上">
<surname>
         井上
        </surname>
</persName>
       、
       <persName corresp="#pers_佐々">
<surname>
         佐々
        </surname>
</persName>
       、
       <persName corresp="#pers_一森">
<surname>
         一森
        </surname>
</persName>
       ノ諸氏来会シ、京釜鉄道会社事業進行ノ順序及役員組織ノ事ヲ熟議ス
      </p>
</div>
<div type="diary-entry" xml:id="DKB10009m-0439">
<head>
<date when="1901-03-15">
        三月十五日
       </date>
</head>
<p>
       曇、午前、
       <persName corresp="#pers_増島六一郎">
<surname>
         増島
        </surname>
<forename>
         六一郎
        </forename>
</persName>
       氏来リ
       <placeName corresp="#place_アメリカ合衆国">
        米国
       </placeName>
       ヨリ資本輸入ノ事、及英人ヒエンチ氏計画ノ鉄道車輛貸与ノ方法ニ付協議アリ、
       <persName corresp="#pers_中村孫兵衛">
<surname>
         中村
        </surname>
<forename>
         孫兵衛
        </forename>
</persName>
       来リ
       <persName corresp="#pers_長谷川武司">
<surname>
         長谷川
        </surname>
<forename>
         武司
        </forename>
</persName>
       ノ事ヲ談ス、
       <persName corresp="#pers_萩原源太郎">
<surname>
         萩原
        </surname>
<forename>
         源太郎
        </forename>
</persName>
       、
       <persName corresp="#pers_佐々木慎思郎">
<surname>
         佐々木
        </surname>
<forename>
         慎思郎
        </forename>
</persName>
       諸氏来ル、
       <time when="16:00:00">
        午後四時
       </time>
       銀行集会所臨時会ニ出席ス、議事畢テ
       <placeName corresp="#place_浜町">
        浜町
       </placeName>
       常盤屋ニ抵リ
       <persName corresp="#pers_外山修造">
<surname>
         外山
        </surname>
<forename>
         修造
        </forename>
</persName>
       氏招宴ニ列ス、夜
       <time when="21:00:00">
        九時
       </time>
<placeName corresp="#place_浜町">
        浜町
       </placeName>
       宅ニ帰宿ス
      </p>
</div>
<div type="diary-entry" xml:id="DKB10009m-0440">
<head>
<date when="1901-03-16">
        三月十六日
       </date>
</head>
<p>
<pb corresp="#pageB1183" facs="https://eiichi.shibusawa.or.jp/denkishiryo-bekkan/api/images/iiif/209/full/max/0/default.jpg" n="B1183" source="#pageB1183"></pb>
</p>
</div>
</body>
</text>
</group>
</text>