<?xml version="1.0" encoding="utf-8"?>
<text type="diary"><group><text n="41000000000" xml:id="DKB10022m"><body><div type="diary-entry" xml:id="DKB10022m-0095"><p>
       ハ上陸シテ直ニ汽車ニテ東上スル者アルニヨリ、夫々伝言ヲ托ス、且上陸後旅行ノ順序ヲ定ム、
       <time when="21:00:00">
        九時
       </time>
<placeName corresp="#place_下関市">
        馬関
       </placeName>
       着、直ニ小蒸気船ニ移リ、
       <orgName>
        春帆楼
       </orgName>
       ニ投宿ス、兼テ書信ニテ打合セ置キタレハ
       <placeName corresp="#place_東京">
        東京
       </placeName>
       ヨリ
       <persName corresp="#pers_渋沢兼子">
<forename>
         兼子
        </forename>
</persName>
       来リ迎ヘ、共ニ旅寓ニ抵ル、投宿後入浴朝飧シテ、数多ノ歓迎者ニ接見ス、休息後大里ナル浅野セメント工場ヲ一覧ス、
       <persName corresp="#pers_辻">
<surname>
         辻
        </surname>
</persName>
       、
       <persName corresp="#pers_須永">
<surname>
         須永
        </surname>
</persName>
       二氏周旋甚タ勉ム、畢テ帰宿、午飧後、商業学校ニ抵リ学生ニ一場ノ講演ヲ為ス、此夜、関門銀行者ノ催ス処ノ招待会ニ出席シテ一場ノ
       <placeName corresp="#place_支那">
        支那
       </placeName>
       視察《（談脱カ）》ヲ為ス、夜
       <time when="22:00:00">
        十時
       </time>
       過散会ス
      </p>
</div>
<div type="diary-entry" xml:id="DKB10022m-0096">
<head>
<date when="1914-06-05">
        六月五日
       </date>
       金　晴　風ナク気候人ニ可ナリ
      </head>
<p>
<time when="06:00:00">
        午前六時
       </time>
       起床、入浴シテ、朝飧ヲ食ス、後、来人ニ接ス、此日ハ曾テ
       <persName corresp="#pers_安川敬一郎">
<surname>
         安川
        </surname>
<forename>
         敬一郎
        </forename>
</persName>
       氏ヨリ案内セラレタル明治専門学校一覧ノ為メ、
       <time when="08:00:00">
        八時
       </time>
       過
       <placeName corresp="#place_下関市">
        馬関
       </placeName>
       ヲ発シ小汽船ニテ
       <placeName corresp="#place_門司">
        門司
       </placeName>
       ニ抵リ、夫ヨリ電車ニ搭シテ
       <placeName corresp="#place_戸畑区">
        戸畑
       </placeName>
       村ニ抵リ停車場ニテ自働車ニ移リ、
       <persName corresp="#pers_安川">
<surname>
         安川
        </surname>
</persName>
       父子ノ案内ニテ学校ニ抵ル、
       <persName corresp="#pers_明石">
<surname>
         明石
        </surname>
</persName>
       、
       <persName corresp="#pers_西条">
<surname>
         西条
        </surname>
</persName>
       二氏モ同行ス、校内各室ヲ詳細ニ一覧シ、参考品陳列所、図書館等マテ巡覧シテ、
       <time when="13:00:00">
        午後一時
       </time>
<persName corresp="#pers_安川">
<surname>
         安川
        </surname>
</persName>
       氏居宅ニ抵リテ午飧会アリ、畢テ又、寄宿舎、浴室、娯楽所等ヲモ一覧シ、
       <time when="15:00:00">
        三時
       </time>
       頃ヨリ講堂ニ於テ一場ノ講演ヲ為ス、後、
       <persName corresp="#pers_安川">
<surname>
         安川
        </surname>
</persName>
       氏宅ニ於テ晩飧会アリ、一同会食ス、専門学校ハ数年前
       <persName corresp="#pers_安川">
<surname>
         安川
        </surname>
</persName>
       氏独力創設ノ校舎ニシテ、工学、採鉱、冶金等総テ実用的ノ学科練習ノ所トス、其大体ハ
       <persName corresp="#pers_山川">
<surname>
         山川
        </surname>
</persName>
       博士参画セシモノニテ、現校長ハ
       <placeName corresp="#place_的場">
        的場
       </placeName>
       博士担任ス、其趣旨実着ニシテ敢テ浮華ノ風ナシ、真ニ理想的ノ修学タリト云フヲ得ヘキナリ、夜食後種々談話シテ、
       <time when="23:00:00">
        十一時
       </time>
       就寝
      </p>
</div>
<div type="diary-entry" xml:id="DKB10022m-0097">
<head>
<date when="1914-06-06">
        六月六日
       </date>
       土　晴　風強クシテ暑気モ稍増加スルヲ覚フ
      </head>
<p>
       ○是日ノ記入ヲ欠ク。
      </p>
</div>
<div type="diary-entry" xml:id="DKB10022m-0098">
<head>
<date when="1914-06-07">
        六月七日
       </date>
       日　晴　風ナクシテ暑気強カラス、夕方ヨリ雨ヲ催スニ似タリ
      </head>
<p>
       ○是日ノ記入ヲ欠ク。
      </p>
</div>
<div type="diary-entry" xml:id="DKB10022m-0099">
<head>
<date when="1914-06-08">
        六月八日
       </date>
       月　曇
       <time when="12:00:00">
        正午
       </time>
       頃ヨリ雨降リ午後益強ク、暑気少ク減スルヲ覚フ
      </head>
<p>
       ○是日ノ記入ヲ欠ク。
      </p>
</div>
<div type="diary-entry" xml:id="DKB10022m-0100">
<head>
<date when="1914-06-09">
        六月九日
       </date>
       火　晴　風ナクシテ暑気昨日ヨリ増加セリ
      </head>
<p>
<time when="06:00:00">
        午前六時
       </time>
       起床、入浴シテ　○以下記入ナシ。
      </p>
</div>
<div type="diary-entry" xml:id="DKB10022m-0101">
<head>
<date when="1914-06-10">
        六月十日
       </date>
       水　晴　風少ク暑気モ酷ナラス
      </head>
<p>
<time when="06:00:00">
        午前六時
       </time>
       起床、入浴シテ、朝飧ヲ食ス、此日ハ当地ヲ出立シテ
       <placeName corresp="#place_下関市">
        馬関
       </placeName>
       ニ赴クノ予定ニシテ、且、途中
       <placeName corresp="#place_中津">
        中津
       </placeName>
       町ニ於テ下車、町内有志者ノ企望ニ応シテ一場ノ
       <placeName corresp="#place_支那">
        支那
       </placeName>
       視察《（談脱カ）》ヲ為ス筈ニテ、
       <time when="07:00:00">
        午前七時
       </time>
       過
       <placeName corresp="#place_別府">
        別府
       </placeName>
       発ノ汽車ニテ出発ス、来リテ行ヲ送ル人多シ、
       <time when="09:00:00">
        九時
       </time>
       過
       <placeName corresp="#place_中津">
        中津
       </placeName>
       着下車、歓迎ノ人ニ案内セラレテ
       <persName corresp="#pers_池大雅">
        大雅堂
       </persName>
       ノ書画アル一寺ヲ訪ヒ、又、故
       <persName corresp="#pers_福沢">
<surname>
         福沢
        </surname>
</persName>
       翁ノ旧宅ヲ一覧ス、町ノ保存スル所ナリ、後、一料理亭ニ於テ午飧ス、食後、学校ニ於テ町民ノ企望ニ応シ一場ノ演説ヲ為ス、来会者数百名、頗ル盛会ナリ、畢テ
       <time when="14:00:00">
        午後二時
       </time>
       過
       <persName corresp="#pers_渋沢兼子">
<forename>
         兼子
        </forename>
</persName>
       ノ来着ヲ待テ共ニ発車シ、
       <time when="16:00:00">
        午後四時
       </time>
       過
       <placeName corresp="#place_下関市">
        馬関
       </placeName>
       着、
       <orgName>
        春帆楼
       </orgName>
       ニ投宿ス、休憩後、地方経済会ノ請求ニ応シテ一場ノ演説ヲ為ス夜食後、此地ニ有名ナル小門ノ夜焚ヲ一覧ス、夜
       <time when="22:00:00">
        十時
       </time>
       帰宿ス
      </p>
</div>
<div type="diary-entry" xml:id="DKB10022m-0102">
<head>
<date when="1914-06-11">
        六月十一日
       </date>
       木　晴　風少ク気候漸ク暑熱ヲ覚フ
      </head>
<p>
<time when="06:00:00">
        午前六時
       </time>
       起床、入浴シテ、朝飧ヲ食ス、
       <orgName>
        日本銀行
       </orgName>
       支店長及地方有志者
       <pb corresp="#pageB1789" facs="https://eiichi.shibusawa.or.jp/denkishiryo-bekkan/api/images/iiif/815/full/max/0/default.jpg" n="B1789" source="#pageB1789"></pb>
</p>
</div>
</body>
</text>
</group>
</text>