<?xml version="1.0" encoding="utf-8"?>
<text type="diary"><group><text n="41000000000" xml:id="DKB10016m"><body><div type="diary-entry" xml:id="DKB10016m-0248"><p>
<lb></lb>
<time when="05:30:00">
        午前五時半
       </time>
       起床、入浴シ、畢テ昨夜落手セシ
       <placeName corresp="#place_東京">
        東京
       </placeName>
       ヨリノ来状ヲ一覧ス
       <time when="07:00:00">
        七時
       </time>
       朝飧ヲ食シ、
       <orgName>
        盛岡銀行
       </orgName>
       重役等ノ来訪ニ接ス、
       <time when="07:40:00">
        午前七時四十分
       </time>
       寓居ヲ出テ
       <placeName corresp="#place_盛岡市">
        盛岡
       </placeName>
       停車場ニ抵リ、
       <time when="08:10:00">
        八時十分
       </time>
       発ノ汽車ニ搭ス、車中海軍士官等ノ
       <placeName corresp="#place_大湊">
        大湊
       </placeName>
       ヨリ帰京スルアリテ頗ル雑沓セリ、
       <placeName corresp="#place_一関市">
        一関
       </placeName>
       駅ニ抵リテ
       <placeName corresp="#place_仙台">
        仙台
       </placeName>
<orgName>
        七十七銀行
       </orgName>
<persName corresp="#pers_神谷">
<surname>
         神谷
        </surname>
</persName>
       氏来リ迎フ、
       <time when="12:00:00">
        十二時
       </time>
<placeName corresp="#place_松島">
        松島
       </placeName>
       駅ニ抵リ、車ヲ下リテ
       <placeName corresp="#place_松島">
        松島
       </placeName>
       ニ抵ル、
       <placeName corresp="#place_松島">
        松島
       </placeName>
       館ニ投宿ス、館ハ本姓ヲ大宮司ト称シ、
       <persName corresp="#pers_北条時頼">
<surname>
         北条
        </surname>
<forename>
         時頼
        </forename>
</persName>
       ノ頃ヨリ連綿トシテ此地ニ継続スルモノナリト云フ、午飧後、先ツ舟ニ乗リテ洲立テト唱フル方法ニテ海中ニ於テ魚ヲ捕ルヲ見ル、後、
       <placeName corresp="#place_松島">
        松島
       </placeName>
       ノ名勝ヲ巡覧ス、瑞巌寺ニテハ廟宇及画幅等ヲ見ル、又、観瀾亭ニ抵リ、更ニ徒歩シテ雄島ニ抵ル、夜ニ入リテ
       <persName corresp="#pers_神谷">
<surname>
         神谷
        </surname>
</persName>
       氏ノ催フセル湾上ノ流灯ヲ見ル、頗ル奇観ナリキ
       <lb></lb>
       夜、
       <persName corresp="#pers_渋沢篤二">
<forename>
         篤二
        </forename>
</persName>
       ヨリ電報アリ、
       <persName corresp="#pers_井上">
<surname>
         井上
        </surname>
</persName>
       侯ノ病状ヲ告ケ来ル、直ニ回答ヲ発ス、又、瓦斯会社
       <persName corresp="#pers_高松">
<surname>
         高松
        </surname>
</persName>
       氏ノ来状ニ答フル為メ発電ス
       <lb></lb>
       （欄外）
       <lb></lb>
       ■■[img図]〓■雨中
       <placeName corresp="#place_松島">
        松島
       </placeName>
       湾に舟を浮へて
       <lb></lb>
       月花のなかめはよそにまかせおきてあめにとひ来し松か
       <placeName corresp="#place_浦島">
        浦島
       </placeName>
</p>
</div>
<div type="diary-entry" xml:id="DKB10016m-0249">
<head>
<date when="1908-09-05">
        九月五日
       </date>
       曇　冷
      </head>
<p>
<time when="05:30:00">
        午前五時半
       </time>
       起床、日記ヲ編成ス、
       <time when="06:00:00">
        六時
       </time>
       朝飧ヲ食シ、
       <time when="07:00:00">
        七時
       </time>
       頃船ニテ旅亭ヲ発シ、
       <placeName corresp="#place_松島">
        松島
       </placeName>
       湾中ヲ巡遊シテ
       <time when="09:00:00">
        九時
       </time>
       塩竈ニ抵ル、舟中ノ眺望佳絶ナリ、
       <placeName corresp="#place_松島">
        松島
       </placeName>
       ニハ
       <placeName corresp="#place_仙台">
        仙台
       </placeName>
       人多ク来リ迎フ、先ツ
       <placeName corresp="#place_塩竈">
        塩竈
       </placeName>
       神社ニ詣シテ後、宮司ノ家ニ休憩ス、
       <persName corresp="#pers_林子平">
<surname>
         林
        </surname>
<forename>
         子平
        </forename>
</persName>
       ノ遺物ヲ携来リテ一見ヲ需ムルモノアリ、
       <time when="11:00:00">
        午前十一時
       </time>
       発ノ汽車ニテ
       <placeName corresp="#place_仙台市">
        仙台市
       </placeName>
       ニ向ヒ、
       <time when="12:00:00">
        十二時
       </time>
<placeName corresp="#place_仙台">
        仙台
       </placeName>
       着、停車場ニハ市長
       <persName corresp="#pers_早川">
<surname>
         早川
        </surname>
</persName>
       氏其他多人数来リ迎フ、停車場ニテ家人ト分レ、
       <persName corresp="#pers_土岐">
<surname>
         土岐
        </surname>
</persName>
       其他
       <orgName>
        七十七銀行
       </orgName>
       諸氏ト共ニ同行ニ抵リテ行務ヲ談ス、畢テ午飧ヲ食シ、行内ヲ一覧シ行員ニ訓示ヲ為シ、
       <time when="15:00:00">
        三時
       </time>
<persName corresp="#pers_寺田">
<surname>
         寺田
        </surname>
</persName>
       知事ヲ訪ヒ、後、県会議事堂ニ抵リ一場ノ経済講話ヲ為ス、来会者三四百名許ナリキ、畢テ陸奥ノ園ト云フ旅亭ニ抵リテ入浴シ、再ヒ旅亭ヲ出テ公園地ニアル挹翠館ニ抵ル、地方人士ノ開催セル歓迎会ニ応スル為メナリ、酒間一場ノ謝詞ヲ述ヘ
       <time when="21:00:00">
        九時
       </time>
       頃帰亭ス、夜、旅亭ニテ
       <persName corresp="#pers_土岐">
<surname>
         土岐
        </surname>
</persName>
       、
       <persName corresp="#pers_神谷">
<surname>
         神谷
        </surname>
</persName>
       氏等来リテ当市ニ有名ナル歌舞ヲ奏セシメテ旅情ヲ慰ス
      </p>
</div>
<div type="diary-entry" xml:id="DKB10016m-0250">
<head>
<date when="1908-09-06">
        九月六日
       </date>
       ○天候ノ記入ヲ欠ク。
      </head>
<p>
<time when="06:00:00">
        午前六時
       </time>
       起床、入浴シ、畢テ朝飧ヲ食ス、
       <time when="07:30:00">
        七時半
       </time>
       旅亭ヲ発シ、
       <persName corresp="#pers_八木久兵衛">
<surname>
         八木
        </surname>
<forename>
         久兵衛
        </forename>
</persName>
       別荘ニ抵ル、蓋シ別荘ハ新築ニ係リ、且
       <placeName corresp="#place_仙台">
        仙台
       </placeName>
       ニ有名ナル埋木ヲ以テ建造セシモノナリト云フ、一覧後直ニ停車場ニ抵ル、
       <persName corresp="#pers_寺田">
<surname>
         寺田
        </surname>
</persName>
       知事、
       <persName corresp="#pers_和達">
<surname>
         和達
        </surname>
</persName>
       市長、
       <persName corresp="#pers_早川知寛">
<surname>
         早川
        </surname>
<forename>
         知寛
        </forename>
</persName>
       、其他市人数十名送リ来ル、
       <time when="08:00:00">
        八時
       </time>
       発ノ汽車ニ搭シ、
       <time when="14:00:00">
        午後二時
       </time>
       過
       <placeName corresp="#place_磐城国">
        磐城国
       </placeName>
<placeName corresp="#place_湯本">
        湯本
       </placeName>
       駅ニ抵ル、
       <persName corresp="#pers_郷隆三郎">
<surname>
         郷
        </surname>
<forename>
         隆三郎
        </forename>
</persName>
       （白煉瓦会社）、
       <persName corresp="#pers_倉田">
<surname>
         倉田
        </surname>
</persName>
       、
       <persName corresp="#pers_岡部">
<surname>
         岡部
        </surname>
</persName>
       二氏（
       <placeName corresp="#place_磐城">
        磐城
       </placeName>
       炭礦会社）等来リ迎フ、昨日ハ電報ヲ以テ下車ノ事ヲ要請セラレシモ、帰京ヲ急ク為メ其意ニ応シ難キ旨回答シタレハ、両会社ハ多数ノ社員ヲシテ停車場ニ集メテ車中ナカラノ会見ヲ望マル、依テ一言ヲ述ヘテ厚意ヲ謝ス、汽車
       <placeName corresp="#place_水戸">
        水戸
       </placeName>
       ニ達スル頃ヨリ夜ニ入リテ四顧寂寥タリ、夜
       <time when="22:00:00">
        十時
       </time>
<placeName corresp="#place_上野">
        上野
       </placeName>
       停車場着、
       <placeName corresp="#place_東京">
        東京
       </placeName>
       ヨリ多数ノ人迎ノ為メ来会セラル、悉ク之ヲ謝シテ、夜
       <time when="23:00:00">
        十一時
       </time>
<placeName corresp="#place_王子">
        王子
       </placeName>
       ニ帰宿ス
      </p>
</div>
<div type="diary-entry" xml:id="DKB10016m-0251">
<head>
<date when="1908-09-07">
        九月七日
       </date>
       曇　冷
      </head>
<p>
<time when="06:00:00">
        午前六時
       </time>
       起床入浴シ、後、朝飧ヲ為ス、
       <time when="07:00:00">
        午前七時
       </time>
       家ヲ出テ
       <placeName corresp="#place_新橋">
        新橋
       </placeName>
       停車場
       <pb corresp="#pageB1535" facs="https://eiichi.shibusawa.or.jp/denkishiryo-bekkan/api/images/iiif/561/full/max/0/default.jpg" n="B1535" source="#pageB1535"></pb>
</p>
</div>
</body>
</text>
</group>
</text>