<?xml version="1.0" encoding="utf-8"?>
<text type="diary"><group><text n="41000000000" xml:id="DKB10013m"><body><div type="diary-entry" xml:id="DKB10013m-0007"><p>
       教育勅語ヲ揮灑ス
       <lb></lb>
       夜、甲子夜話ヲ読ム
      </p>
</div>
<div type="diary-entry" xml:id="DKB10013m-0008">
<head>
<date when="1905-01-08">
        一月八日
       </date>
       日　晴　少シク風アリ
      </head>
<p>
<time when="07:15:00">
        午前七時十五分
       </time>
       起床、室内運動後、朝飧ヲ喫ス
       <lb></lb>
       食後又教育ノ詔ヲ書ス、
       <time when="10:00:00">
        十時
       </time>
<persName corresp="#pers_竹田政智">
<surname>
         竹田
        </surname>
<forename>
         政智
        </forename>
</persName>
       、
       <persName corresp="#pers_田中元三郎">
<surname>
         田中
        </surname>
<forename>
         元三郎
        </forename>
</persName>
       二氏来リ
       <orgName>
        人造肥料会社
       </orgName>
       ニテ買入ヘキ燐礦石ノ事ヲ談シ、且本月ノ株主総会ニ提出スヘキ増株ニ関スル議案ヲ協議シ、燐礦ニ付テハ明日
       <orgName>
        イリス商会
       </orgName>
       ニ照会スヘキ事トシ、且来ル
       <date evidence="year inferenced, month" when="1905-01-14">
        十四日
       </date>
       午後
       <placeName corresp="#place_日本橋兜町">
        兜町
       </placeName>
       ニ重役会ヲ開ク事ヲ約ス、
       <orgName>
        第一銀行
       </orgName>
<persName corresp="#pers_佐々木">
<surname>
         佐々木
        </surname>
</persName>
       氏ニ書状ヲ発シ
       <persName corresp="#pers_尾高">
<surname>
         尾高
        </surname>
</persName>
       来状ヲ封入一覧セシム、
       <persName corresp="#pers_八十島親徳">
<surname>
         八十島
        </surname>
<forename>
         親徳
        </forename>
</persName>
       ニ二回ノ書状ヲ送ル、
       <persName corresp="#pers_渋沢作太郎">
<surname>
         渋沢
        </surname>
<forename>
         作太郎
        </forename>
</persName>
       、
       <persName corresp="#pers_梅浦精一">
<surname>
         梅浦
        </surname>
<forename>
         精一
        </forename>
</persName>
       二氏来訪セラル
       <lb></lb>
<time when="16:00:00">
        午後四時
       </time>
       ヨリ
       <placeName corresp="#place_大磯町">
        大磯
       </placeName>
       市街ヲ散歩シ
       <time when="17:00:00">
        五時
       </time>
       帰寓ス、
       <persName corresp="#pers_前田青莎">
<surname>
         前田
        </surname>
<forename>
         青莎
        </forename>
</persName>
       氏来リ岩越鉄道会社ノ重役談アリ
       <lb></lb>
       夜、甲子夜話ヲ読ム
      </p>
</div>
<div type="diary-entry" xml:id="DKB10013m-0009">
<head>
<date when="1905-01-09">
        一月九日
       </date>
       月　晴　風寒シ
      </head>
<p>
<time when="07:15:00">
        午前七時十五分
       </time>
       起床、例ノ如ク室内ノ運動ヲ為ス、
       <time when="08:00:00">
        八時
       </time>
       過朝飧ヲ畢リ日記ヲ編成ス、畢テ揮毫ヲ試ム
       <lb></lb>
       午後、東京
       <orgName>
        人造肥料会社
       </orgName>
       ヨリ電話来ルヲ以テ其回答ヲ発スル為郵便局ニ抵リ、
       <persName corresp="#pers_竹田政智">
<surname>
         竹田
        </surname>
<forename>
         政智
        </forename>
</persName>
       氏ニ電話シテ燐石五千噸
       <orgName>
        イリス商会
       </orgName>
       ニ注文ノ事ヲ照会ス、畢テ市中ヲ散歩シテ
       <time when="17:00:00">
        五時
       </time>
       帰寓、入浴ス
       <lb></lb>
       夜、甲子夜話ヲ読ム
       <lb></lb>
       此日腹部ノ工合悪ク、為メテ《（ニ）》粥ヲ食シテ他食ヲ禁ス
      </p>
</div>
<div type="diary-entry" xml:id="DKB10013m-0010">
<head>
<date when="1905-01-10">
        一月十日
       </date>
       火　晴　風寒シ
      </head>
<p>
<time when="07:00:00">
        午前七時
       </time>
       起床、室内運動ヲ為シ朝飧ヲ畢ル
       <lb></lb>
<time when="09:00:00">
        九時
       </time>
<persName corresp="#pers_佐々木勇之助">
<surname>
         佐々木
        </surname>
<forename>
         勇之助
        </forename>
</persName>
       氏来訪ス、
       <orgName>
        第一銀行
       </orgName>
       株主総会ノ事ニ関シテ種々ノ協議ヲ為シ、議案及報告書ノ文章ヲ議シ、且其字句ヲ修正ス、
       <time when="13:00:00">
        午後一時
       </time>
       帰京ス、後、又昨日ノ如ク揮毫ヲ試ム、
       <time when="14:00:00">
        二時
       </time>
       過
       <persName corresp="#pers_仙石貢">
<surname>
         仙石
        </surname>
<forename>
         貢
        </forename>
</persName>
       氏来話ス、
       <persName corresp="#pers_仙石">
<surname>
         仙石
        </surname>
</persName>
       氏帰リ去テ後亦少シク揮毫ヲ為シ、
       <time when="16:00:00">
        四時
       </time>
       頃ヨリ郊外ヲ散歩ス、
       <time when="17:00:00">
        五時
       </time>
       過帰寓ス
       <lb></lb>
       夜、甲子夜話ヲ読ム
       <lb></lb>
<orgName>
        石川島造船所
       </orgName>
<persName corresp="#pers_平沢">
<surname>
         平沢
        </surname>
</persName>
       氏ヨリ来翰アリ、
       <persName corresp="#pers_戸塚">
<surname>
         戸塚
        </surname>
</persName>
       持参ス、依テ回答ヲ作リテ同人ニ托シ并テ
       <persName corresp="#pers_八十島親徳">
<surname>
         八十島
        </surname>
<forename>
         親徳
        </forename>
</persName>
       ヘ書状ヲ発ス、但同人ヨリノ二回ノ来書ニ答ヘ且要件ヲ通知スル為メナリ
      </p>
</div>
<div type="diary-entry" xml:id="DKB10013m-0011">
<head>
<date when="1905-01-11">
        一月十一日
       </date>
       水　○天候ノ記入ヲ欠ク。
      </head>
<p>
<time when="07:30:00">
        午前七時半
       </time>
       起床、室内運動ヲ為ス、
       <time when="08:30:00">
        八時半
       </time>
       朝飧ヲ畢ル、
       <time when="09:00:00">
        九時
       </time>
       頃
       <persName corresp="#pers_植村澄三郎">
<surname>
         植村
        </surname>
<forename>
         澄三郎
        </forename>
</persName>
       氏来訪ス、緩談午飧ヲ共ニス、
       <time when="13:00:00">
        午後一時
       </time>
<placeName corresp="#place_東京">
        東京
       </placeName>
       ヘ帰る
       <lb></lb>
<persName corresp="#pers_佐々木清麿">
<surname>
         佐々木
        </surname>
<forename>
         清麿
        </forename>
</persName>
       ヨリ大坂紡績会社当季決算ノ事ヲ通リ《（シカ）》来ル、
       <time when="16:00:00">
        午後四時
       </time>
       過キ郊外ニ散歩シ高麗神社ニ詣ス、
       <time when="17:00:00">
        五時
       </time>
       後帰寓ス
       <lb></lb>
       夜、甲子夜話ヲ読ム
      </p>
</div>
<div type="diary-entry" xml:id="DKB10013m-0012">
<head>
<date when="1905-01-12">
        一月十二日
       </date>
       木　晴　風ナシ
      </head>
<p>
<time when="07:00:00">
        午前七時
       </time>
       起床、室内運動ヲ為シ、
       <time when="08:00:00">
        八時
       </time>
       朝飧ヲ畢ル
       <lb></lb>
<time when="09:00:00">
        九時
       </time>
       頃ヨリ又揮毫ヲ試ム、午飧後
       <persName corresp="#pers_山田堤雲">
<surname>
         山田
        </surname>
<forename>
         堤雲
        </forename>
</persName>
       来訪セラル、
       <time when="13:00:00">
        一時
       </time>
       過キ市街ニ散歩シテ理髪ヲ為ス、
       <time when="15:00:00">
        三時
       </time>
       帰宿ス
       <lb></lb>
<persName corresp="#pers_加藤末郎">
<surname>
         加藤
        </surname>
<forename>
         末郎
        </forename>
</persName>
       来訪、韓国興業会社ノ事業着手ノ次第ヲ聴ク、
       <date when="1905-01-16">
        十六日
       </date>
<placeName corresp="#place_東京">
        東京
       </placeName>
       ニテ面会ヲ約シテ去ル
       <lb></lb>
<pb corresp="#pageB1346" facs="https://eiichi.shibusawa.or.jp/denkishiryo-bekkan/api/images/iiif/372/full/max/0/default.jpg" n="B1346" source="#pageB1346"></pb>
</p>
</div>
</body>
</text>
</group>
</text>