<?xml version="1.0" encoding="utf-8"?>
<text type="diary"><front><div type="preface" xml:id="DKB10000c-0001">
<p>
     滞仏中の「航西日記」「御巡国日録」「
     <placeName corresp="#place_イギリス">
      英国
     </placeName>
     御巡行日誌」「
     <placeName corresp="#place_パリ">
      巴里
     </placeName>
     御在館日記」「御用日記」等は本資料第一巻に収められているのでここには収録していない。
    </p>
<p>
     右の手帖に続いて現存している日記は和綴小型の横帳に記入されたもので、日付は
     <date type="旧暦" when="1869-11-24">
      明治二年十月二十一日
     </date>
     から
     <date type="旧暦" when="1869-12-21">
      十一月十九日
     </date>
     までのものである。尤も、日記の記入は横帳の中途からで、巻頭の部分には常平倉関係の文書の写が記入されている。この事は、この横帳が手控として用いられていた事を示している。やがて
     <persName corresp="#pers_渋沢栄一">
<forename>
       栄一
      </forename>
</persName>
     は
     <date type="旧暦" when="1869-11-11">
      十月八日
     </date>
     付で中央政府から呼出されて上京するが、その時、改めて日記を記し出した。「
     <date type="旧暦" when="1869-11-24">
      明治二年己巳十月廿一日
     </date>
     」と起筆の日を記しているのは注意すべきであろう。
     <persName corresp="#pers_渋沢栄一">
<forename>
       栄一
      </forename>
</persName>
     の生涯の一転機ともいうべき時期である。
    </p>
<p>
     この横帳には後半に「見廻書類請払」として、民部省に在って取扱った書類の控が記されているが、この全文は本資料第二巻第二一三頁以下に収録してあるのでここには収録していない。
    </p>
<p>
     以後、
     <date when="1899">
      明治三十二年
     </date>
     に至るまで正確な日記体のものは残っていない。
     <date when="1884">
      明治十七年
     </date>
     と、
     <date when="1886">
      十九年
     </date>
     に短時日の日記があるが、共に旅行に出た折の記録で、二種とも携帯に便利な小型手帖が用いられ、記入も旅行中の記事のみであって、余白には漢詩や覚書が書きこまれてあるのである。
    </p>
<p>
     後に表示するように
     <date when="1899">
      明治三十二年
     </date>
     から
     <date when="1930">
      昭和五年
     </date>
     までは断続はあっても一応揃っている。
     <date when="1899">
      三十二年
     </date>
     になって用い初めた机上日記（博文館発行）には扉に
     <persName corresp="#pers_渋沢栄一">
<forename>
       栄一
      </forename>
</persName>
     の手跡で「第一号」と記されているのは、この時から日記を初めたという意味にも取れるし、机上日記の第一号と見れば、これ以前に日記があったとも思えるが、
     <date when="1869">
      明治二年
     </date>
     後、旅行中の日記を省けば日記らしいものは現在していない。
    </p>
<p>
     机上日記は五冊用いていて
     <date when="1904-04">
      三十七年四月
     </date>
     まであるが、各年に新しく出版されたのを用いたのではなく、
     <date when="1898">
      三十一年
     </date>
     出版のもの五冊に逐次書きこんで行ったものである。机上日記は自由日記のように頁ごとに月日の印刷がないので順次書き入れていて、新年になっても改めることはなく、そのまま書き続けて行っている。第一冊に「第一号」、第二冊目に「第二号」、第三冊目に「第三号」と記入しているが、それ以後この
     <pb corresp="#pageB1f17" facs="https://eiichi.shibusawa.or.jp/denkishiryo-bekkan/api/images/iiif/17/full/max/0/default.jpg" n="B1f17" source="#pageB1f17"></pb>
</p>
</div>
</front>
</text>